src/__init__.py
src/main.py
src/images/__init__.py
src/images/convert_image_to_ascii.py
src/videos/__init__.py
src/videos/convert_video_to_ascii.py
convert_image_video_to_ascii-0.0.1.dist-info/LICENSE
convert_image_video_to_ascii-0.0.1.dist-info/METADATA
convert_image_video_to_ascii-0.0.1.dist-info/WHEEL
convert_image_video_to_ascii-0.0.1.dist-info/entry_points.txt
convert_image_video_to_ascii-0.0.1.dist-info/top_level.txt
convert_image_video_to_ascii-0.0.1.dist-info/RECORD
