Metadata-Version: 2.1
Name: convert-image-video-to-ascii
Version: 0.0.1
Summary: A simple program that converts images , videos and livefeed videos to ASCII art.
Home-page: https://github.com/Mo2men-dev/convert-image-video-to-ascii
Author: Momen Sameh
Author-email: momensameh5@gmail.com
Classifier: Programming Language :: Python :: 3
Classifier: License :: OSI Approved :: MIT License
Classifier: Operating System :: OS Independent
Requires-Python: >=3.6
License-File: LICENSE
